SIONLexer.py
SIONParser.py
SIONVisitor.py
sion.py
sion-0.2.2.dist-info/METADATA
sion-0.2.2.dist-info/RECORD
sion-0.2.2.dist-info/WHEEL
sion-0.2.2.dist-info/top_level.txt
