Metadata-Version: 2.1
Name: sion
Version: 0.2.2
Summary: loading and dumping a SION format file
Home-page: https://github.com/kamimura/py-sion
Author: kamimura
Author-email: kamimura@live.jp
License: MIT
Platform: UNKNOWN
Classifier: Programming Language :: Python :: 3
Classifier: License :: OSI Approved :: MIT License
Classifier: Operating System :: OS Independent
Classifier: Environment :: Console
Requires-Dist: antlr4-python3-runtime
